falk/__init__.py
falk/apps.py
falk/component_registry.py
falk/component_templates.py
falk/components.py
falk/dependency_injection.py
falk/errors.py
falk/extra_template_context.py
falk/file_uploads.py
falk/hashing.py
falk/http.py
falk/immutable_proxy.py
falk/import_strings.py
falk/node_ids.py
falk/pytest_plugin.py
falk/rendering.py
falk/request_handling.py
falk/routing.py
falk/secrets.py
falk/static_files.py
falk/tokens.py
falk/version.py
falk/asgi/__init__.py
falk/asgi/app.py
falk/asgi/file_responses.py
falk/asgi/helper.py
falk/asgi/lifespans.py
falk/asgi/multipart.py
falk/asgi/request_handling.py
falk/asgi/websockets.py
falk/contrib/__init__.py
falk/contrib/django/__init__.py
falk/contrib/django/auth.py
falk/middlewares/__init__.py
falk/middlewares/static_files.py
falk/providers/__init__.py
falk/providers/callbacks.py
falk/providers/flags.py
falk/providers/middlewares.py
falk/providers/requests.py
falk/providers/responses.py
falk/providers/routing.py
falk/providers/static_files.py
falk/static/falk/falk.js
falk/utils/__init__.py
falk/utils/environment.py
falk/utils/iterables.py
falk/utils/path.py
falk-0.2.5.dist-info/licenses/LICENSE.txt
falk-0.2.5.dist-info/METADATA
falk-0.2.5.dist-info/WHEEL
falk-0.2.5.dist-info/entry_points.txt
falk-0.2.5.dist-info/top_level.txt
falk-0.2.5.dist-info/RECORD
