Metadata-Version: 2.4
Name: falk
Version: 0.2.5
Author-email: Florian Scherf <mail@florianscherf.de>
Requires-Python: >=3.9
License-File: LICENSE.txt
Requires-Dist: jinja2
Requires-Dist: simple-logging-setup
Requires-Dist: aiofiles
Requires-Dist: python-multipart
Provides-Extra: dev
Requires-Dist: uvicorn[standard]; extra == "dev"
Requires-Dist: watchfiles; extra == "dev"
Requires-Dist: rlpython; extra == "dev"
Provides-Extra: test
Requires-Dist: coverage==7.10.4; extra == "test"
Requires-Dist: pytest==8.4.1; extra == "test"
Requires-Dist: pytest-playwright==0.7.2; extra == "test"
Requires-Dist: requests; extra == "test"
Requires-Dist: rlpython; extra == "test"
Requires-Dist: uvicorn[standard]; extra == "test"
Requires-Dist: starlette; extra == "test"
Requires-Dist: Django~=5.2; extra == "test"
Provides-Extra: docs
Requires-Dist: mkdocs==1.6.1; extra == "docs"
Requires-Dist: mkdocstrings[python]==0.28.2; extra == "docs"
Requires-Dist: mkdocs-material==9.6.6; extra == "docs"
Requires-Dist: grip==4.6.2; extra == "docs"
Dynamic: license-file
